MANIFEST.in
README.txt
setup.py
docs/HISTORY.txt
docs/LICENSE.txt
src/stxnext/__init__.py
src/stxnext.transform.avi2flv.egg-info/PKG-INFO
src/stxnext.transform.avi2flv.egg-info/SOURCES.txt
src/stxnext.transform.avi2flv.egg-info/dependency_links.txt
src/stxnext.transform.avi2flv.egg-info/entry_points.txt
src/stxnext.transform.avi2flv.egg-info/namespace_packages.txt
src/stxnext.transform.avi2flv.egg-info/not-zip-safe
src/stxnext.transform.avi2flv.egg-info/requires.txt
src/stxnext.transform.avi2flv.egg-info/top_level.txt
src/stxnext/transform/__init__.py
src/stxnext/transform/avi2flv/__init__.py
src/stxnext/transform/avi2flv/avi2flv.py
src/stxnext/transform/avi2flv/avi2flv.txt
src/stxnext/transform/avi2flv/avi_to_flv.py
src/stxnext/transform/avi2flv/avi_to_flv.txt
src/stxnext/transform/avi2flv/browser.txt
src/stxnext/transform/avi2flv/configure.zcml
src/stxnext/transform/avi2flv/patches.py
src/stxnext/transform/avi2flv/patches.zcml
src/stxnext/transform/avi2flv/setuphandlers.py
src/stxnext/transform/avi2flv/version.txt
src/stxnext/transform/avi2flv/Extensions/install.py
src/stxnext/transform/avi2flv/profiles/default/metadata.xml
src/stxnext/transform/avi2flv/profiles/default/stxnext.transform.avi2flv.txt
src/stxnext/transform/avi2flv/profiles/uninstall/stxnext.transform.avi2flv-uninstall.txt
src/stxnext/transform/avi2flv/tests/__init__.py
src/stxnext/transform/avi2flv/tests/tests.py
src/stxnext/transform/avi2flv/tests/data/README.txt