Metadata-Version: 1.0
Name: stxnext.transform.avi2flv
Version: 0.2.1
Summary: Converts clips from AVI format to FLV during upload to Plone.
Home-page: http://www.stxnext.pl/open-source
Author: STX Next Sp. z o.o, Wojciech Lichota, Maciej Zięba
Author-email: info@stxnext.pl
License: Zope Public License, Version 2.1 (ZPL)
Keywords: plone avi flv movie clip flash video
Platform: any
Classifier: Development Status :: 3 - Alpha
Classifier: Framework :: Zope2
Classifier: Framework :: Plone
Classifier: Intended Audience :: Developers
Classifier: License :: OSI Approved :: Zope Public License
Classifier: Natural Language :: English
Classifier: Programming Language :: Python
